vultr_dns_mcp/__init__.py
vultr_dns_mcp/_version.py
vultr_dns_mcp/cli.py
vultr_dns_mcp/client.py
vultr_dns_mcp/py.typed
vultr_dns_mcp/server.py
vultr_dns_mcp-1.0.4.dist-info/licenses/LICENSE
vultr_dns_mcp-1.0.4.dist-info/METADATA
vultr_dns_mcp-1.0.4.dist-info/WHEEL
vultr_dns_mcp-1.0.4.dist-info/entry_points.txt
vultr_dns_mcp-1.0.4.dist-info/top_level.txt
vultr_dns_mcp-1.0.4.dist-info/RECORD
