Metadata-Version: 2.4
Name: vultr-dns-mcp
Version: 1.0.4
Summary: A comprehensive Model Context Protocol (MCP) server for managing Vultr DNS records
Author-email: Ryan Malloy <ryan@supported.systems>
Maintainer-email: Ryan Malloy <ryan@supported.systems>
License-Expression: MIT
Project-URL: Homepage, https://github.com/rsp2k/vultr-dns-mcp
Project-URL: Documentation, https://vultr-dns-mcp.readthedocs.io/
Project-URL: Repository, https://github.com/rsp2k/vultr-dns-mcp.git
Project-URL: Bug Tracker, https://github.com/rsp2k/vultr-dns-mcp/issues
Project-URL: Changelog, https://github.com/rsp2k/vultr-dns-mcp/blob/main/CHANGELOG.md
Keywords: vultr,dns,mcp,model-context-protocol,dns-management,api,mcp-server
Classifier: Development Status :: 5 - Production/Stable
Classifier: Intended Audience :: Developers
Classifier: Intended Audience :: System Administrators
Classifier: Operating System :: OS Independent
Classifier: Programming Language :: Python :: 3
Classifier: Programming Language :: Python :: 3.10
Classifier: Programming Language :: Python :: 3.11
Classifier: Programming Language :: Python :: 3.12
Classifier: Programming Language :: Python :: 3.13
Classifier: Topic :: Internet :: Name Service (DNS)
Classifier: Topic :: System :: Systems Administration
Classifier: Topic :: Software Development :: Libraries :: Python Modules
Classifier: Topic :: Communications
Classifier: Environment :: Console
Classifier: Framework :: AsyncIO
Requires-Python: >=3.10
License-File: LICENSE
Requires-Dist: mcp>=1.0.0
Requires-Dist: httpx>=0.24.0
Requires-Dist: pydantic>=2.0.0
Requires-Dist: click>=8.0.0
Provides-Extra: dev
Requires-Dist: black>=23.0.0; extra == "dev"
Requires-Dist: ruff>=0.1.0; extra == "dev"
Requires-Dist: mypy>=1.0.0; extra == "dev"
Requires-Dist: pre-commit>=3.0.0; extra == "dev"
Provides-Extra: test
Requires-Dist: pytest>=7.0.0; extra == "test"
Requires-Dist: pytest-asyncio>=0.21.0; extra == "test"
Requires-Dist: pytest-cov>=4.0.0; extra == "test"
Requires-Dist: pytest-mock>=3.10.0; extra == "test"
Requires-Dist: coverage[toml]>=7.0.0; extra == "test"
Provides-Extra: docs
Requires-Dist: sphinx>=6.0.0; extra == "docs"
Requires-Dist: sphinx-rtd-theme>=1.2.0; extra == "docs"
Requires-Dist: myst-parser>=1.0.0; extra == "docs"
Dynamic: license-file
